LICENSE
MANIFEST.in
README.rst
setup.py
md2img/__init__.py
md2img/logo.png
md2img/main.py
md2img/text.txt
md2img.egg-info/PKG-INFO
md2img.egg-info/SOURCES.txt
md2img.egg-info/dependency_links.txt
md2img.egg-info/requires.txt
md2img.egg-info/top_level.txt
md2img/fonts/sarasa-mono-sc-bold.ttf
md2img/fonts/sarasa-mono-sc-bolditalic.ttf
md2img/fonts/sarasa-mono-sc-italic.ttf
md2img/fonts/sarasa-mono-sc-regular.ttf