Metadata-Version: 2.1
Name: md2img
Version: 0.0.2
Summary: Markdown text to image
Home-page: https://fishc.com.cn
Author: FishC
Author-email: 205204@qq.com
License: GNU GPLv3 License
Platform: all
Classifier: Intended Audience :: Developers
Classifier: Operating System :: OS Independent
Classifier: Natural Language :: Chinese (Simplified)
Classifier: Programming Language :: Python
Classifier: Programming Language :: Python :: 3
Classifier: Topic :: Software Development :: Libraries
License-File: LICENSE
